mdformat_gofmt/__init__.py
mdformat_gofmt-0.0.2.dist-info/entry_points.txt
mdformat_gofmt-0.0.2.dist-info/LICENSE
mdformat_gofmt-0.0.2.dist-info/WHEEL
mdformat_gofmt-0.0.2.dist-info/METADATA
mdformat_gofmt-0.0.2.dist-info/RECORD
