Metadata-Version: 2.1
Name: mdformat-gofmt
Version: 0.0.2
Summary: Mdformat plugin to gofmt Go code blocks
Home-page: https://github.com/hukkinj1/mdformat-gofmt
License: MIT
Keywords: mdformat,markdown,commonmark,formatter
Author: Taneli Hukkinen
Author-email: hukkinj1@users.noreply.github.com
Requires-Python: >=3.6.1,<4.0.0
Classifier: License :: OSI Approved :: MIT License
Classifier: Programming Language :: Python :: 3
Classifier: Programming Language :: Python :: 3.7
Classifier: Programming Language :: Python :: 3.8
Classifier: Programming Language :: Python :: 3.9
Classifier: Topic :: Documentation
Classifier: Topic :: Text Processing :: Markup
Classifier: Typing :: Typed
Requires-Dist: mdformat (>=0.3.5)
Project-URL: Repository, https://github.com/hukkinj1/mdformat-gofmt
